netz/__init__.py
netz/parser.py
netz-0.1.2.dist-info/WHEEL
netz-0.1.2.dist-info/METADATA
netz-0.1.2.dist-info/RECORD
